kaskuspy/__init__.py
kaskuspy/core.py
kaskuspy/exceptions.py
kaskuspy/hammer.py
kaskuspy-1.1.2.dist-info/LICENSE
kaskuspy-1.1.2.dist-info/METADATA
kaskuspy-1.1.2.dist-info/WHEEL
kaskuspy-1.1.2.dist-info/top_level.txt
kaskuspy-1.1.2.dist-info/RECORD
