Metadata-Version: 2.1
Name: kaskuspy
Version: 1.1.2
Summary: Kaskus Private API Wrapper
Home-page: https://github.com/Shivelight/kaskus-py
Author: Arkie
Author-email: cwkfr@protonmail.com
License: MIT
Platform: UNKNOWN
Classifier: Development Status :: 4 - Beta
Classifier: License :: OSI Approved :: MIT License
Classifier: Programming Language :: Python
Classifier: Programming Language :: Python :: 3
Classifier: Programming Language :: Python :: 3.6
Classifier: Topic :: Software Development :: Libraries
Classifier: Topic :: Software Development :: Libraries :: Python Modules
Requires-Python: >=3.6.0
Requires-Dist: requests
